README.md
setup.py
dalysis/__init__.py
dalysis/table.py
dalysis/typecv.py
dalysis.egg-info/PKG-INFO
dalysis.egg-info/SOURCES.txt
dalysis.egg-info/dependency_links.txt
dalysis.egg-info/requires.txt
dalysis.egg-info/top_level.txt