Metadata-Version: 2.1
Name: dalysis
Version: 0.0.2
Summary: Data anlysis tools with table operate for csv and excel
Home-page: https://github.com/Tikmoing/datanlysis
Author: Youryanmi
Author-email: tikmoing@gmail.com
License: UNKNOWN
Keywords: data anlysis with table
Platform: UNKNOWN
